madsci/experiment_application/__init__.py
madsci/experiment_application/experiment_application.py
madsci_experiment_application-0.6.1.dist-info/METADATA
madsci_experiment_application-0.6.1.dist-info/WHEEL
madsci_experiment_application-0.6.1.dist-info/entry_points.txt
madsci_experiment_application-0.6.1.dist-info/RECORD
