Metadata-Version: 2.1
Name: madsci.experiment_application
Version: 0.6.1
Summary: The Modular Autonomous Discovery for Science (MADSci) Experiment Application framework.
Author-Email: Tobias Ginsburg <tginsburg@anl.gov>, "Ryan D. Lewis" <ryan.lewis@anl.gov>, Casey Stone <cstone@anl.gov>, Doga Ozgulbas <dozgulbas@anl.gov>
License: MIT
Project-URL: Homepage, https://github.com/AD-SDL/MADSci
Requires-Python: >=3.9.1
Requires-Dist: madsci.common
Requires-Dist: madsci.client
Requires-Dist: madsci.node_module
Requires-Dist: rich>=10.0.0
Requires-Dist: pydantic>=2.0.0
Requires-Dist: typing-extensions>=4.0.0
